autolrtuner/__init__.py
autolrtuner/autolrtuner.py
autolrtuner-1.0.2.dist-info/LICENSE
autolrtuner-1.0.2.dist-info/METADATA
autolrtuner-1.0.2.dist-info/WHEEL
autolrtuner-1.0.2.dist-info/top_level.txt
autolrtuner-1.0.2.dist-info/RECORD
