Metadata-Version: 2.1
Name: autolrtuner
Version: 1.0.2
Summary: Heuristically optimize learning rates in neural networks through subsampling loss differentials.
Author: Adam Wu
Author-email: adamwu1@outlook.com
License: MIT License
Project-URL: homepage, https://github.com/adamvvu/autolrtuner
Project-URL: documentation, https://github.com/adamvvu/autolrtuner
Project-URL: repository, https://github.com/adamvvu/autolrtuner
Keywords: tensorflow,hyperparameter tuning,neural networks,deep learning,learning rate,machine learning,artificial intelligence
Classifier: Intended Audience :: Science/Research
Classifier: Topic :: Scientific/Engineering :: Artificial Intelligence
Classifier: Topic :: Scientific/Engineering :: Information Analysis
Classifier: Programming Language :: Python
Classifier: Operating System :: OS Independent
Classifier: License :: OSI Approved :: MIT License
Requires-Python: >=3.8
License-File: LICENSE
Requires-Dist: tensorflow
Requires-Dist: tqdm
Requires-Dist: numpy
Requires-Dist: pandas
Requires-Dist: scipy
Requires-Dist: matplotlib
